nexus_fastapi/__init__.py
nexus_fastapi/cli.py
nexus_fastapi/hooks.py
nexus_fastapi/scaffolds.py
nexus_fastapi-0.1.1.dist-info/METADATA
nexus_fastapi-0.1.1.dist-info/WHEEL
nexus_fastapi-0.1.1.dist-info/entry_points.txt
nexus_fastapi-0.1.1.dist-info/licenses/LICENSE
nexus_fastapi-0.1.1.dist-info/RECORD
