Metadata-Version: 2.4
Name: nexus-fastapi
Version: 0.1.1
Summary: A FastAPI project generator and framework
Project-URL: Homepage, https://github.com/m3et2001/nexus-fastapi
Project-URL: Documentation, https://github.com/m3et2001/nexus-fastapi/blob/main/README.md
Project-URL: Repository, https://github.com/meetvelani/nexus-fastapi.git
Project-URL: Issues, https://github.com/meetvelani/nexus-fastapi/issues
Author-email: Meetkumar velani <meetvelani2728@gmail.com>, Axay Patoliya <axaypatoliya2222@gmail.com>
License-File: LICENSE
Classifier: Development Status :: 3 - Alpha
Classifier: Framework :: FastAPI
Classifier: License :: OSI Approved :: MIT License
Classifier: Operating System :: OS Independent
Classifier: Programming Language :: Python :: 3
Requires-Python: >=3.8
Requires-Dist: alembic>=1.12.1
Requires-Dist: bcrypt>=4.0.1
Requires-Dist: black>=23.11.0
Requires-Dist: email-validator>=2.1.0
Requires-Dist: fastapi>=0.104.1
Requires-Dist: flake8>=6.1.0
Requires-Dist: httpx>=0.25.1
Requires-Dist: isort>=5.12.0
Requires-Dist: passlib>=1.7.4
Requires-Dist: pydantic-settings>=2.1.0
Requires-Dist: pydantic>=2.5.0
Requires-Dist: pytest>=7.4.3
Requires-Dist: python-dotenv>=1.0.0
Requires-Dist: python-jose[cryptography]>=3.3.0
Requires-Dist: python-multipart>=0.0.6
Requires-Dist: sqlalchemy>=2.0.23
Requires-Dist: uvicorn[standard]>=0.24.0
